Metadata-Version: 1.0
Name: cards-imarshall
Version: 0.2
Summary: Python Card Deck Module
Home-page: https://github.com/IanNMarshall/cards_imarshall
Author: IanNMarshall
Author-email: ian.nicholas.marshall@gmail.com
License: MIT
Platform: UNKNOWN
